helloworld.py
Mrhellotesthere-0.0.20.dist-info/METADATA
Mrhellotesthere-0.0.20.dist-info/WHEEL
Mrhellotesthere-0.0.20.dist-info/top_level.txt
Mrhellotesthere-0.0.20.dist-info/RECORD
