Metadata-Version: 2.1
Name: Mrhellotesthere
Version: 0.0.20
Summary: Say hello
Author: NeuralNine (Florian Dedov)
Author-email: <mail@neuralnine.com>
